zdao/__cls_aide_dao_db_types__.py
zdao/__cls_aide_dao_model_column__.py
zdao/__cls_aide_dao_model_main__.py
zdao/__example__.py
zdao/__init__.py
zdao-3.8.dist-info/METADATA
zdao-3.8.dist-info/WHEEL
zdao-3.8.dist-info/top_level.txt
zdao-3.8.dist-info/RECORD
