Metadata-Version: 2.1
Name: zdao
Version: 3.8
Summary: A useless database access model
Home-page: https://github.com/zzt/zdao.git
Author: zhstack
Author-email: zhstack@163.com
License: MIT
Keywords: zdao
